[
  {"partno": "uc3a0512", "names": ["AT32UC3A0512", "AT32UC3A0512AU"], "modes": ["AVR32JTAG", "aWire"]},
  {"partno": "89S51", "names": ["AT89S51"], "modes": ["ISP", "HVPP"]},
  {"partno": "89S52", "names": ["AT89S52"], "modes": ["ISP", "HVPP"]},
  {"partno": "c128", "names": ["AT90CAN128"], "modes": ["SPM", "ISP", "HVPP", "JTAG", "JTAGmkI"]},
  {"partno": "c32", "names": ["AT90CAN32"], "modes": ["SPM", "ISP", "HVPP", "JTAG"]},
  {"partno": "c64", "names": ["AT90CAN64"], "modes": ["SPM", "ISP", "HVPP", "JTAG"]},
  {"partno": "pwm1", "names": ["AT90PWM1"], "modes": ["SPM", "ISP", "HVPP", "debugWIRE"]},
  {"partno": "pwm161", "names": ["AT90PWM161"], "modes": ["SPM", "ISP", "HVPP", "debugWIRE"]},
  {"partno": "pwm2", "names": ["AT90PWM2"], "modes": ["SPM", "ISP", "HVPP", "debugWIRE"]},
  {"partno": "pwm216", "names": ["AT90PWM216"], "modes": ["SPM", "ISP", "HVPP", "debugWIRE"]},
  {"partno": "pwm2b", "names": ["AT90PWM2B"], "modes": ["SPM", "ISP", "HVPP", "debugWIRE"]},
  {"partno": "pwm3", "names": ["AT90PWM3"], "modes": ["SPM", "ISP", "HVPP", "debugWIRE"]},
  {"partno": "pwm316", "names": ["AT90PWM316"], "modes": ["SPM", "ISP", "HVPP", "debugWIRE"]},
  {"partno": "pwm3b", "names": ["AT90PWM3B"], "modes": ["SPM", "ISP", "HVPP", "debugWIRE"]},
  {"partno": "pwm81", "names": ["AT90PWM81", "AT90PWM81EP"], "modes": ["SPM", "ISP", "HVPP", "debugWIRE"]},
  {"partno": "1200", "names": ["AT90S1200", "AT90S1200A"], "modes": ["SPM", "ISP", "HVPP"]},
  {"partno": "2313", "names": ["AT90S2313"], "modes": ["SPM", "ISP", "HVPP"]},
  {"partno": "2323", "names": ["AT90S2323"], "modes": ["SPM", "ISP", "HVSP"]},
  {"partno": "2333", "names": ["AT90S2333"], "modes": ["SPM", "ISP", "HVPP"]},
  {"partno": "2343", "names": ["AT90S2343"], "modes": ["SPM", "ISP", "HVSP"]},
  {"partno": "4414", "names": ["AT90S4414"], "modes": ["SPM", "ISP", "HVPP"]},
  {"partno": "4433", "names": ["AT90S4433"], "modes": ["SPM", "ISP", "HVPP"]},
  {"partno": "4434", "names": ["AT90S4434"], "modes": ["SPM", "ISP", "HVPP"]},
  {"partno": "8515", "names": ["AT90S8515"], "modes": ["SPM", "ISP", "HVPP"]},
  {"partno": "8535", "names": ["AT90S8535"], "modes": ["SPM", "ISP", "HVPP"]},
  {"partno": "usb1286", "names": ["AT90USB1286"], "modes": ["SPM", "ISP", "HVPP", "JTAG"]},
  {"partno": "usb1287", "names": ["AT90USB1287"], "modes": ["SPM", "ISP", "HVPP", "JTAG"]},
  {"partno": "usb162", "names": ["AT90USB162"], "modes": ["SPM", "ISP", "HVPP", "debugWIRE"]},
  {"partno": "usb646", "names": ["AT90USB646"], "modes": ["SPM", "ISP", "HVPP", "JTAG"]},
  {"partno": "usb647", "names": ["AT90USB647"], "modes": ["SPM", "ISP", "HVPP", "JTAG"]},
  {"partno": "usb82", "names": ["AT90USB82"], "modes": ["SPM", "ISP", "HVPP", "debugWIRE"]},
  {"partno": "a5505", "names": ["ATA5505"], "modes": ["SPM", "ISP", "HVPP", "debugWIRE"]},
  {"partno": "a6612c", "names": ["ATA6612C"], "modes": ["SPM", "ISP", "HVPP", "debugWIRE"]},
  {"partno": "a6613c", "names": ["ATA6613C"], "modes": ["SPM", "ISP", "HVPP", "debugWIRE"]},
  {"partno": "a6614q", "names": ["ATA6614Q"], "modes": ["SPM", "ISP", "HVPP", "debugWIRE"]},
  {"partno": "a6616c", "names": ["ATA6616C"], "modes": ["SPM", "ISP", "HVPP", "debugWIRE"]},
  {"partno": "a6617c", "names": ["ATA6617C"], "modes": ["SPM", "ISP", "HVPP", "debugWIRE"]},
  {"partno": "a664251", "names": ["ATA664251"], "modes": ["SPM", "ISP", "HVPP", "debugWIRE"]},
  {"partno": "m103", "names": ["ATmega103", "ATmega103L"], "modes": ["SPM", "ISP", "HVPP"]},
  {"partno": "m128", "names": ["ATmega128", "ATmega128L"], "modes": ["SPM", "ISP", "HVPP", "JTAG", "JTAGmkI"]},
  {"partno": "m1280", "names": ["ATmega1280", "ATmega1280V"], "modes": ["SPM", "ISP", "HVPP", "JTAG"]},
  {"partno": "m1281", "names": ["ATmega1281", "ATmega1281V"], "modes": ["SPM", "ISP", "HVPP", "JTAG"]},
  {"partno": "m1284", "names": ["ATmega1284"], "modes": ["SPM", "ISP", "HVPP", "JTAG"]},
  {"partno": "m1284p", "names": ["ATmega1284P"], "modes": ["SPM", "ISP", "HVPP", "JTAG"]},
  {"partno": "m1284rfr2", "names": ["ATmega1284RFR2"], "modes": ["SPM", "ISP", "HVPP", "JTAG"]},
  {"partno": "m128a", "names": ["ATmega128A"], "modes": ["SPM", "ISP", "HVPP", "JTAG", "JTAGmkI"]},
  {"partno": "m128rfa1", "names": ["ATmega128RFA1"], "modes": ["SPM", "ISP", "HVPP", "JTAG"]},
  {"partno": "m128rfr2", "names": ["ATmega128RFR2"], "modes": ["SPM", "ISP", "HVPP", "JTAG"]},
  {"partno": "m16", "names": ["ATmega16", "ATmega16L"], "modes": ["SPM", "ISP", "HVPP", "JTAG", "JTAGmkI"]},
  {"partno": "m1608", "names": ["ATmega1608"], "modes": ["SPM", "UPDI"]},
  {"partno": "m1609", "names": ["ATmega1609"], "modes": ["SPM", "UPDI"]},
  {"partno": "m161", "names": ["ATmega161", "ATmega161L"], "modes": ["SPM", "ISP", "HVPP"]},
  {"partno": "m162", "names": ["ATmega162", "ATmega162L", "ATmega162V"], "modes": ["SPM", "ISP", "HVPP", "JTAG", "JTAGmkI"]},
  {"partno": "m163", "names": ["ATmega163", "ATmega163L"], "modes": ["SPM", "ISP", "HVPP"]},
  {"partno": "m164a", "names": ["ATmega164A"], "modes": ["SPM", "ISP", "HVPP", "JTAG"]},
  {"partno": "m164p", "names": ["ATmega164P", "ATmega164PV"], "modes": ["SPM", "ISP", "HVPP", "JTAG"]},
  {"partno": "m164pa", "names": ["ATmega164PA"], "modes": ["SPM", "ISP", "HVPP", "JTAG"]},
  {"partno": "m165", "names": ["ATmega165", "ATmega165V"], "modes": ["SPM", "ISP", "HVPP", "JTAG"]},
  {"partno": "m165a", "names": ["ATmega165A"], "modes": ["SPM", "ISP", "HVPP", "JTAG"]},
  {"partno": "m165p", "names": ["ATmega165P", "ATmega165PV"], "modes": ["SPM", "ISP", "HVPP", "JTAG"]},
  {"partno": "m165pa", "names": ["ATmega165PA"], "modes": ["SPM", "ISP", "HVPP", "JTAG"]},
  {"partno": "m168", "names": ["ATmega168", "ATmega168V"], "modes": ["SPM", "ISP", "HVPP", "debugWIRE"]},
  {"partno": "m168a", "names": ["ATmega168A"], "modes": ["SPM", "ISP", "HVPP", "debugWIRE"]},
  {"partno": "m168p", "names": ["ATmega168P", "ATmega168PV"], "modes": ["SPM", "ISP", "HVPP", "debugWIRE"]},
  {"partno": "m168pa", "names": ["ATmega168PA"], "modes": ["SPM", "ISP", "HVPP", "debugWIRE"]},
  {"partno": "m168pb", "names": ["ATmega168PB"], "modes": ["SPM", "ISP", "HVPP", "debugWIRE"]},
  {"partno": "m169", "names": ["ATmega169", "ATmega169L", "ATmega169V"], "modes": ["SPM", "ISP", "HVPP", "JTAG", "JTAGmkI"]},
  {"partno": "m169a", "names": ["ATmega169A"], "modes": ["SPM", "ISP", "HVPP", "JTAG", "JTAGmkI"]},
  {"partno": "m169p", "names": ["ATmega169P", "ATmega169PV"], "modes": ["SPM", "ISP", "HVPP", "JTAG"]},
  {"partno": "m169pa", "names": ["ATmega169PA"], "modes": ["SPM", "ISP", "HVPP", "JTAG"]},
  {"partno": "m16a", "names": ["ATmega16A"], "modes": ["SPM", "ISP", "HVPP", "JTAG", "JTAGmkI"]},
  {"partno": "m16hva", "names": ["ATmega16HVA"], "modes": ["SPM", "ISP", "HVSP", "debugWIRE"]},
  {"partno": "m16hvb", "names": ["ATmega16HVB"], "modes": ["SPM", "ISP", "HVPP", "debugWIRE"]},
  {"partno": "m16hvbrevb", "names": ["ATmega16HVBrevB", "ATMEGA16HVB"], "modes": ["SPM", "ISP", "HVPP", "debugWIRE"]},
  {"partno": "m16m1", "names": ["ATmega16M1"], "modes": ["SPM", "ISP", "HVPP", "debugWIRE"]},
  {"partno": "m16u2", "names": ["ATmega16U2"], "modes": ["SPM", "ISP", "HVPP", "debugWIRE"]},
  {"partno": "m16u4", "names": ["ATmega16U4", "ATmega16U4RC"], "modes": ["SPM", "ISP", "HVPP", "JTAG"]},
  {"partno": "m2560", "names": ["ATmega2560", "ATmega2560V"], "modes": ["SPM", "ISP", "HVPP", "JTAG"]},
  {"partno": "m2561", "names": ["ATmega2561", "ATmega2561V"], "modes": ["SPM", "ISP", "HVPP", "JTAG"]},
  {"partno": "m2564rfr2", "names": ["ATmega2564RFR2"], "modes": ["SPM", "ISP", "HVPP", "JTAG"]},
  {"partno": "m256rfr2", "names": ["ATmega256RFR2"], "modes": ["SPM", "ISP", "HVPP", "JTAG"]},
  {"partno": "m32", "names": ["ATmega32", "ATmega32L"], "modes": ["SPM", "ISP", "HVPP", "JTAG", "JTAGmkI"]},
  {"partno": "m3208", "names": ["ATmega3208"], "modes": ["SPM", "UPDI"]},
  {"partno": "m3209", "names": ["ATmega3209"], "modes": ["SPM", "UPDI"]},
  {"partno": "m324a", "names": ["ATmega324A"], "modes": ["SPM", "ISP", "HVPP", "JTAG"]},
  {"partno": "m324p", "names": ["ATmega324P", "ATmega324PV"], "modes": ["SPM", "ISP", "HVPP", "JTAG"]},
  {"partno": "m324pa", "names": ["ATmega324PA"], "modes": ["SPM", "ISP", "HVPP", "JTAG"]},
  {"partno": "m324pb", "names": ["ATmega324PB"], "modes": ["SPM", "ISP", "HVPP", "JTAG"]},
  {"partno": "m325", "names": ["ATmega325", "ATmega325V"], "modes": ["SPM", "ISP", "HVPP", "JTAG"]},
  {"partno": "m3250", "names": ["ATmega3250", "ATmega3250V"], "modes": ["SPM", "ISP", "HVPP", "JTAG"]},
  {"partno": "m3250a", "names": ["ATmega3250A"], "modes": ["SPM", "ISP", "HVPP", "JTAG"]},
  {"partno": "m3250p", "names": ["ATmega3250P", "ATmega3250PV"], "modes": ["SPM", "ISP", "HVPP", "JTAG"]},
  {"partno": "m3250pa", "names": ["ATmega3250PA"], "modes": ["SPM", "ISP", "HVPP", "JTAG"]},
  {"partno": "m325a", "names": ["ATmega325A"], "modes": ["SPM", "ISP", "HVPP", "JTAG"]},
  {"partno": "m325p", "names": ["ATmega325P", "ATmega325PV"], "modes": ["SPM", "ISP", "HVPP", "JTAG"]},
  {"partno": "m325pa", "names": ["ATmega325PA"], "modes": ["SPM", "ISP", "HVPP", "JTAG"]},
  {"partno": "m328", "names": ["ATmega328"], "modes": ["SPM", "ISP", "HVPP", "debugWIRE"]},
  {"partno": "m328p", "names": ["ATmega328P"], "modes": ["SPM", "ISP", "HVPP", "debugWIRE"]},
  {"partno": "m328pb", "names": ["ATmega328PB"], "modes": ["SPM", "ISP", "HVPP", "debugWIRE"]},
  {"partno": "m329", "names": ["ATmega329", "ATmega329V"], "modes": ["SPM", "ISP", "HVPP", "JTAG"]},
  {"partno": "m3290", "names": ["ATmega3290", "ATmega3290V"], "modes": ["SPM", "ISP", "HVPP", "JTAG"]},
  {"partno": "m3290a", "names": ["ATmega3290A"], "modes": ["SPM", "ISP", "HVPP", "JTAG"]},
  {"partno": "m3290p", "names": ["ATmega3290P", "ATmega3290PV"], "modes": ["SPM", "ISP", "HVPP", "JTAG"]},
  {"partno": "m3290pa", "names": ["ATmega3290PA"], "modes": ["SPM", "ISP", "HVPP", "JTAG"]},
  {"partno": "m329a", "names": ["ATmega329A"], "modes": ["SPM", "ISP", "HVPP", "JTAG"]},
  {"partno": "m329p", "names": ["ATmega329P", "ATmega329PV"], "modes": ["SPM", "ISP", "HVPP", "JTAG"]},
  {"partno": "m329pa", "names": ["ATmega329PA"], "modes": ["SPM", "ISP", "HVPP", "JTAG"]},
  {"partno": "m32a", "names": ["ATmega32A"], "modes": ["SPM", "ISP", "HVPP", "JTAG", "JTAGmkI"]},
  {"partno": "m32c1", "names": ["ATmega32C1"], "modes": ["SPM", "ISP", "HVPP", "debugWIRE"]},
  {"partno": "m32hvb", "names": ["ATmega32HVB"], "modes": ["SPM", "ISP", "HVPP", "debugWIRE"]},
  {"partno": "m32hvbrevb", "names": ["ATmega32HVBrevB", "ATMEGA32HVB"], "modes": ["SPM", "ISP", "HVPP", "debugWIRE"]},
  {"partno": "m32hve2", "names": ["ATmega32HVE2"], "modes": ["SPM", "ISP", "HVSP", "debugWIRE"]},
  {"partno": "m32m1", "names": ["ATmega32M1"], "modes": ["SPM", "ISP", "HVPP", "debugWIRE"]},
  {"partno": "m32u2", "names": ["ATmega32U2"], "modes": ["SPM", "ISP", "HVPP", "debugWIRE"]},
  {"partno": "m32u4", "names": ["ATmega32U4", "ATmega32U4RC"], "modes": ["SPM", "ISP", "HVPP", "JTAG"]},
  {"partno": "m406", "names": ["ATmega406"], "modes": ["SPM", "HVPP", "JTAG"]},
  {"partno": "m48", "names": ["ATmega48", "ATmega48V"], "modes": ["SPM", "ISP", "HVPP", "debugWIRE"]},
  {"partno": "m4808", "names": ["ATmega4808"], "modes": ["SPM", "UPDI"]},
  {"partno": "m4809", "names": ["ATmega4809"], "modes": ["SPM", "UPDI"]},
  {"partno": "m48a", "names": ["ATmega48A"], "modes": ["SPM", "ISP", "HVPP", "debugWIRE"]},
  {"partno": "m48p", "names": ["ATmega48P", "ATmega48PV"], "modes": ["SPM", "ISP", "HVPP", "debugWIRE"]},
  {"partno": "m48pa", "names": ["ATmega48PA"], "modes": ["SPM", "ISP", "HVPP", "debugWIRE"]},
  {"partno": "m48pb", "names": ["ATmega48PB"], "modes": ["SPM", "ISP", "HVPP", "debugWIRE"]},
  {"partno": "m64", "names": ["ATmega64", "ATmega64L"], "modes": ["SPM", "ISP", "HVPP", "JTAG", "JTAGmkI"]},
  {"partno": "m640", "names": ["ATmega640", "ATmega640V"], "modes": ["SPM", "ISP", "HVPP", "JTAG"]},
  {"partno": "m644", "names": ["ATmega644", "ATmega644V"], "modes": ["SPM", "ISP", "HVPP", "JTAG"]},
  {"partno": "m644a", "names": ["ATmega644A"], "modes": ["SPM", "ISP", "HVPP", "JTAG"]},
  {"partno": "m644p", "names": ["ATmega644P", "ATmega644PV"], "modes": ["SPM", "ISP", "HVPP", "JTAG"]},
  {"partno": "m644pa", "names": ["ATmega644PA"], "modes": ["SPM", "ISP", "HVPP", "JTAG"]},
  {"partno": "m644rfr2", "names": ["ATmega644RFR2"], "modes": ["SPM", "ISP", "HVPP", "JTAG"]},
  {"partno": "m645", "names": ["ATmega645", "ATmega645V"], "modes": ["SPM", "ISP", "HVPP", "JTAG"]},
  {"partno": "m6450", "names": ["ATmega6450", "ATmega6450V"], "modes": ["SPM", "ISP", "HVPP", "JTAG"]},
  {"partno": "m6450a", "names": ["ATmega6450A"], "modes": ["SPM", "ISP", "HVPP", "JTAG"]},
  {"partno": "m6450p", "names": ["ATmega6450P"], "modes": ["SPM", "ISP", "HVPP", "JTAG"]},
  {"partno": "m645a", "names": ["ATmega645A"], "modes": ["SPM", "ISP", "HVPP", "JTAG"]},
  {"partno": "m645p", "names": ["ATmega645P"], "modes": ["SPM", "ISP", "HVPP", "JTAG"]},
  {"partno": "m649", "names": ["ATmega649", "ATmega649V"], "modes": ["SPM", "ISP", "HVPP", "JTAG"]},
  {"partno": "m6490", "names": ["ATmega6490", "ATmega6490V"], "modes": ["SPM", "ISP", "HVPP", "JTAG"]},
  {"partno": "m6490a", "names": ["ATmega6490A"], "modes": ["SPM", "ISP", "HVPP", "JTAG"]},
  {"partno": "m6490p", "names": ["ATmega6490P"], "modes": ["SPM", "ISP", "HVPP", "JTAG"]},
  {"partno": "m649a", "names": ["ATmega649A"], "modes": ["SPM", "ISP", "HVPP", "JTAG"]},
  {"partno": "m649p", "names": ["ATmega649P"], "modes": ["SPM", "ISP", "HVPP", "JTAG"]},
  {"partno": "m64a", "names": ["ATmega64A"], "modes": ["SPM", "ISP", "HVPP", "JTAG", "JTAGmkI"]},
  {"partno": "m64c1", "names": ["ATmega64C1"], "modes": ["SPM", "ISP", "HVPP", "debugWIRE"]},
  {"partno": "m64hve2", "names": ["ATmega64HVE2"], "modes": ["SPM", "ISP", "HVSP", "debugWIRE"]},
  {"partno": "m64m1", "names": ["ATmega64M1"], "modes": ["SPM", "ISP", "HVPP", "debugWIRE"]},
  {"partno": "m64rfr2", "names": ["ATmega64RFR2"], "modes": ["SPM", "ISP", "HVPP", "JTAG"]},
  {"partno": "m8", "names": ["ATmega8", "ATmega8L"], "modes": ["SPM", "ISP", "HVPP"]},
  {"partno": "m808", "names": ["ATmega808"], "modes": ["SPM", "UPDI"]},
  {"partno": "m809", "names": ["ATmega809"], "modes": ["SPM", "UPDI"]},
  {"partno": "m8515", "names": ["ATmega8515", "ATmega8515L"], "modes": ["SPM", "ISP", "HVPP"]},
  {"partno": "m8535", "names": ["ATmega8535", "ATmega8535L"], "modes": ["SPM", "ISP", "HVPP"]},
  {"partno": "m88", "names": ["ATmega88", "ATmega88V"], "modes": ["SPM", "ISP", "HVPP", "debugWIRE"]},
  {"partno": "m88a", "names": ["ATmega88A"], "modes": ["SPM", "ISP", "HVPP", "debugWIRE"]},
  {"partno": "m88p", "names": ["ATmega88P", "ATmega88PV"], "modes": ["SPM", "ISP", "HVPP", "debugWIRE"]},
  {"partno": "m88pa", "names": ["ATmega88PA"], "modes": ["SPM", "ISP", "HVPP", "debugWIRE"]},
  {"partno": "m88pb", "names": ["ATmega88PB"], "modes": ["SPM", "ISP", "HVPP", "debugWIRE"]},
  {"partno": "m8a", "names": ["ATmega8A"], "modes": ["SPM", "ISP", "HVPP"]},
  {"partno": "m8hva", "names": ["ATmega8HVA"], "modes": ["SPM", "ISP", "HVSP", "debugWIRE"]},
  {"partno": "m8u2", "names": ["ATmega8U2"], "modes": ["SPM", "ISP", "HVPP", "debugWIRE"]},
  {"partno": "t10", "names": ["ATtiny10"], "modes": ["TPI"]},
  {"partno": "t102", "names": ["ATtiny102", "ATtiny102F"], "modes": ["TPI"]},
  {"partno": "t104", "names": ["ATtiny104", "ATtiny104F"], "modes": ["TPI"]},
  {"partno": "t11", "names": ["ATtiny11", "ATtiny11L"], "modes": ["HVSP"]},
  {"partno": "t12", "names": ["ATtiny12", "ATtiny12L", "ATtiny12V"], "modes": ["ISP", "HVSP"]},
  {"partno": "t13", "names": ["ATtiny13", "ATtiny13V"], "modes": ["SPM", "ISP", "HVSP", "debugWIRE"]},
  {"partno": "t13a", "names": ["ATtiny13A"], "modes": ["SPM", "ISP", "HVSP", "debugWIRE"]},
  {"partno": "t15", "names": ["ATtiny15", "ATtiny15L"], "modes": ["ISP", "HVSP"]},
  {"partno": "t1604", "names": ["ATtiny1604"], "modes": ["SPM", "UPDI"]},
  {"partno": "t1606", "names": ["ATtiny1606"], "modes": ["SPM", "UPDI"]},
  {"partno": "t1607", "names": ["ATtiny1607"], "modes": ["SPM", "UPDI"]},
  {"partno": "t1614", "names": ["ATtiny1614"], "modes": ["SPM", "UPDI"]},
  {"partno": "t1616", "names": ["ATtiny1616"], "modes": ["SPM", "UPDI"]},
  {"partno": "t1617", "names": ["ATtiny1617"], "modes": ["SPM", "UPDI"]},
  {"partno": "t1624", "names": ["ATtiny1624"], "modes": ["SPM", "UPDI"]},
  {"partno": "t1626", "names": ["ATtiny1626"], "modes": ["SPM", "UPDI"]},
  {"partno": "t1627", "names": ["ATtiny1627"], "modes": ["SPM", "UPDI"]},
  {"partno": "t1634", "names": ["ATtiny1634", "ATtiny1634R"], "modes": ["SPM", "ISP", "HVPP", "debugWIRE"]},
  {"partno": "t1634r", "names": ["ATtiny1634R"], "modes": ["SPM", "ISP", "HVPP", "debugWIRE"]},
  {"partno": "t167", "names": ["ATtiny167"], "modes": ["SPM", "ISP", "HVPP", "debugWIRE"]},
  {"partno": "t20", "names": ["ATtiny20"], "modes": ["TPI"]},
  {"partno": "t202", "names": ["ATtiny202"], "modes": ["SPM", "UPDI"]},
  {"partno": "t204", "names": ["ATtiny204"], "modes": ["SPM", "UPDI"]},
  {"partno": "t212", "names": ["ATtiny212"], "modes": ["SPM", "UPDI"]},
  {"partno": "t214", "names": ["ATtiny214"], "modes": ["SPM", "UPDI"]},
  {"partno": "t22", "names": ["ATtiny22", "ATtiny22L"], "modes": ["SPM", "ISP", "HVSP"]},
  {"partno": "t2313", "names": ["ATtiny2313", "ATtiny2313V"], "modes": ["SPM", "ISP", "HVPP", "debugWIRE"]},
  {"partno": "t2313a", "names": ["ATtiny2313A"], "modes": ["SPM", "ISP", "HVPP", "debugWIRE"]},
  {"partno": "t24", "names": ["ATtiny24", "ATtiny24V"], "modes": ["SPM", "ISP", "HVSP", "debugWIRE"]},
  {"partno": "t24a", "names": ["ATtiny24A"], "modes": ["SPM", "ISP", "HVSP", "debugWIRE"]},
  {"partno": "t25", "names": ["ATtiny25", "ATtiny25V"], "modes": ["SPM", "ISP", "HVSP", "debugWIRE"]},
  {"partno": "t26", "names": ["ATtiny26", "ATtiny26L"], "modes": ["ISP", "HVPP"]},
  {"partno": "t261", "names": ["ATtiny261", "ATtiny261V"], "modes": ["SPM", "ISP", "HVPP", "debugWIRE"]},
  {"partno": "t261a", "names": ["ATtiny261A"], "modes": ["SPM", "ISP", "HVPP", "debugWIRE"]},
  {"partno": "t28", "names": ["ATtiny28", "ATtiny28L", "ATtiny28V"], "modes": ["HVPP"]},
  {"partno": "t3216", "names": ["ATtiny3216"], "modes": ["SPM", "UPDI"]},
  {"partno": "t3217", "names": ["ATtiny3217"], "modes": ["SPM", "UPDI"]},
  {"partno": "t3224", "names": ["ATtiny3224"], "modes": ["SPM", "UPDI"]},
  {"partno": "t3226", "names": ["ATtiny3226"], "modes": ["SPM", "UPDI"]},
  {"partno": "t3227", "names": ["ATtiny3227"], "modes": ["SPM", "UPDI"]},
  {"partno": "t4", "names": ["ATtiny4"], "modes": ["TPI"]},
  {"partno": "t40", "names": ["ATtiny40"], "modes": ["TPI"]},
  {"partno": "t402", "names": ["ATtiny402"], "modes": ["SPM", "UPDI"]},
  {"partno": "t404", "names": ["ATtiny404"], "modes": ["SPM", "UPDI"]},
  {"partno": "t406", "names": ["ATtiny406"], "modes": ["SPM", "UPDI"]},
  {"partno": "t412", "names": ["ATtiny412"], "modes": ["SPM", "UPDI"]},
  {"partno": "t414", "names": ["ATtiny414"], "modes": ["SPM", "UPDI"]},
  {"partno": "t416", "names": ["ATtiny416"], "modes": ["SPM", "UPDI"]},
  {"partno": "t416auto", "names": ["ATtiny416auto", "ATtiny416"], "modes": ["SPM", "UPDI"]},
  {"partno": "t417", "names": ["ATtiny417"], "modes": ["SPM", "UPDI"]},
  {"partno": "t424", "names": ["ATtiny424"], "modes": ["SPM", "UPDI"]},
  {"partno": "t426", "names": ["ATtiny426"], "modes": ["SPM", "UPDI"]},
  {"partno": "t427", "names": ["ATtiny427"], "modes": ["SPM", "UPDI"]},
  {"partno": "t4313", "names": ["ATtiny4313"], "modes": ["SPM", "ISP", "HVPP", "debugWIRE"]},
  {"partno": "t43u", "names": ["ATtiny43U"], "modes": ["SPM", "ISP", "HVPP", "debugWIRE"]},
  {"partno": "t44", "names": ["ATtiny44", "ATtiny44V"], "modes": ["SPM", "ISP", "HVSP", "debugWIRE"]},
  {"partno": "t441", "names": ["ATtiny441"], "modes": ["SPM", "ISP", "HVSP", "debugWIRE"]},
  {"partno": "t44a", "names": ["ATtiny44A"], "modes": ["SPM", "ISP", "HVSP", "debugWIRE"]},
  {"partno": "t45", "names": ["ATtiny45", "ATtiny45V"], "modes": ["SPM", "ISP", "HVSP", "debugWIRE"]},
  {"partno": "t461", "names": ["ATtiny461", "ATtiny461V"], "modes": ["SPM", "ISP", "HVPP", "debugWIRE"]},
  {"partno": "t461a", "names": ["ATtiny461A"], "modes": ["SPM", "ISP", "HVPP", "debugWIRE"]},
  {"partno": "t48", "names": ["ATtiny48"], "modes": ["SPM", "ISP", "HVPP", "debugWIRE"]},
  {"partno": "t5", "names": ["ATtiny5"], "modes": ["TPI"]},
  {"partno": "t804", "names": ["ATtiny804"], "modes": ["SPM", "UPDI"]},
  {"partno": "t806", "names": ["ATtiny806"], "modes": ["SPM", "UPDI"]},
  {"partno": "t807", "names": ["ATtiny807"], "modes": ["SPM", "UPDI"]},
  {"partno": "t814", "names": ["ATtiny814"], "modes": ["SPM", "UPDI"]},
  {"partno": "t816", "names": ["ATtiny816"], "modes": ["SPM", "UPDI"]},
  {"partno": "t817", "names": ["ATtiny817"], "modes": ["SPM", "UPDI"]},
  {"partno": "t824", "names": ["ATtiny824"], "modes": ["SPM", "UPDI"]},
  {"partno": "t826", "names": ["ATtiny826"], "modes": ["SPM", "UPDI"]},
  {"partno": "t827", "names": ["ATtiny827"], "modes": ["SPM", "UPDI"]},
  {"partno": "t828", "names": ["ATtiny828", "ATtiny828R"], "modes": ["SPM", "ISP", "HVPP", "debugWIRE"]},
  {"partno": "t828r", "names": ["ATtiny828R"], "modes": ["SPM", "ISP", "HVPP", "debugWIRE"]},
  {"partno": "t84", "names": ["ATtiny84", "ATtiny84V"], "modes": ["SPM", "ISP", "HVSP", "debugWIRE"]},
  {"partno": "t841", "names": ["ATtiny841"], "modes": ["SPM", "ISP", "HVSP", "debugWIRE"]},
  {"partno": "t84a", "names": ["ATtiny84A"], "modes": ["SPM", "ISP", "HVSP", "debugWIRE"]},
  {"partno": "t85", "names": ["ATtiny85", "ATtiny85V"], "modes": ["SPM", "ISP", "HVSP", "debugWIRE"]},
  {"partno": "t861", "names": ["ATtiny861", "ATtiny861V"], "modes": ["SPM", "ISP", "HVPP", "debugWIRE"]},
  {"partno": "t861a", "names": ["ATtiny861A"], "modes": ["SPM", "ISP", "HVPP", "debugWIRE"]},
  {"partno": "t87", "names": ["ATtiny87"], "modes": ["SPM", "ISP", "HVPP", "debugWIRE"]},
  {"partno": "t88", "names": ["ATtiny88"], "modes": ["SPM", "ISP", "HVPP", "debugWIRE"]},
  {"partno": "t9", "names": ["ATtiny9"], "modes": ["TPI"]},
  {"partno": "x128a1", "names": ["ATxmega128A1"], "modes": ["SPM", "PDI", "XMEGAJTAG"]},
  {"partno": "x128a1d", "names": ["ATxmega128A1revD"], "modes": ["SPM", "PDI", "XMEGAJTAG"]},
  {"partno": "x128a1u", "names": ["ATxmega128A1U"], "modes": ["SPM", "PDI", "XMEGAJTAG"]},
  {"partno": "x128a3", "names": ["ATxmega128A3"], "modes": ["SPM", "PDI", "XMEGAJTAG"]},
  {"partno": "x128a3u", "names": ["ATxmega128A3U"], "modes": ["SPM", "PDI", "XMEGAJTAG"]},
  {"partno": "x128a4", "names": ["ATxmega128A4"], "modes": ["SPM", "PDI", "XMEGAJTAG"]},
  {"partno": "x128a4u", "names": ["ATxmega128A4U"], "modes": ["SPM", "PDI"]},
  {"partno": "x128b1", "names": ["ATxmega128B1"], "modes": ["SPM", "PDI", "XMEGAJTAG"]},
  {"partno": "x128b3", "names": ["ATxmega128B3"], "modes": ["SPM", "PDI", "XMEGAJTAG"]},
  {"partno": "x128c3", "names": ["ATxmega128C3"], "modes": ["SPM", "PDI"]},
  {"partno": "x128d3", "names": ["ATxmega128D3"], "modes": ["SPM", "PDI"]},
  {"partno": "x128d4", "names": ["ATxmega128D4"], "modes": ["SPM", "PDI"]},
  {"partno": "x16a4", "names": ["ATxmega16A4"], "modes": ["SPM", "PDI"]},
  {"partno": "x16a4u", "names": ["ATxmega16A4U"], "modes": ["SPM", "PDI"]},
  {"partno": "x16c4", "names": ["ATxmega16C4"], "modes": ["SPM", "PDI"]},
  {"partno": "x16d4", "names": ["ATxmega16D4"], "modes": ["SPM", "PDI"]},
  {"partno": "x16e5", "names": ["ATxmega16E5"], "modes": ["SPM", "PDI"]},
  {"partno": "x192a1", "names": ["ATxmega192A1"], "modes": ["SPM", "PDI", "XMEGAJTAG"]},
  {"partno": "x192a3", "names": ["ATxmega192A3"], "modes": ["SPM", "PDI", "XMEGAJTAG"]},
  {"partno": "x192a3u", "names": ["ATxmega192A3U"], "modes": ["SPM", "PDI", "XMEGAJTAG"]},
  {"partno": "x192c3", "names": ["ATxmega192C3"], "modes": ["SPM", "PDI"]},
  {"partno": "x192d3", "names": ["ATxmega192D3"], "modes": ["SPM", "PDI"]},
  {"partno": "x256a1", "names": ["ATxmega256A1"], "modes": ["SPM", "PDI", "XMEGAJTAG"]},
  {"partno": "x256a3", "names": ["ATxmega256A3"], "modes": ["SPM", "PDI", "XMEGAJTAG"]},
  {"partno": "x256a3b", "names": ["ATxmega256A3B"], "modes": ["SPM", "PDI", "XMEGAJTAG"]},
  {"partno": "x256a3bu", "names": ["ATxmega256A3BU"], "modes": ["SPM", "PDI", "XMEGAJTAG"]},
  {"partno": "x256a3u", "names": ["ATxmega256A3U"], "modes": ["SPM", "PDI", "XMEGAJTAG"]},
  {"partno": "x256c3", "names": ["ATxmega256C3"], "modes": ["SPM", "PDI"]},
  {"partno": "x256d3", "names": ["ATxmega256D3"], "modes": ["SPM", "PDI"]},
  {"partno": "x32a4", "names": ["ATxmega32A4"], "modes": ["SPM", "PDI"]},
  {"partno": "x32a4u", "names": ["ATxmega32A4U"], "modes": ["SPM", "PDI"]},
  {"partno": "x32c3", "names": ["ATxmega32C3"], "modes": ["SPM", "PDI"]},
  {"partno": "x32c4", "names": ["ATxmega32C4"], "modes": ["SPM", "PDI"]},
  {"partno": "x32d3", "names": ["ATxmega32D3"], "modes": ["SPM", "PDI"]},
  {"partno": "x32d4", "names": ["ATxmega32D4"], "modes": ["SPM", "PDI"]},
  {"partno": "x32e5", "names": ["ATxmega32E5"], "modes": ["SPM", "PDI"]},
  {"partno": "x384c3", "names": ["ATxmega384C3"], "modes": ["SPM", "PDI"]},
  {"partno": "x384d3", "names": ["ATxmega384D3"], "modes": ["SPM", "PDI"]},
  {"partno": "x64a1", "names": ["ATxmega64A1"], "modes": ["SPM", "PDI", "XMEGAJTAG"]},
  {"partno": "x64a1u", "names": ["ATxmega64A1U"], "modes": ["SPM", "PDI", "XMEGAJTAG"]},
  {"partno": "x64a3", "names": ["ATxmega64A3"], "modes": ["SPM", "PDI", "XMEGAJTAG"]},
  {"partno": "x64a3u", "names": ["ATxmega64A3U"], "modes": ["SPM", "PDI", "XMEGAJTAG"]},
  {"partno": "x64a4", "names": ["ATxmega64A4"], "modes": ["SPM", "PDI", "XMEGAJTAG"]},
  {"partno": "x64a4u", "names": ["ATxmega64A4U"], "modes": ["SPM", "PDI"]},
  {"partno": "x64b1", "names": ["ATxmega64B1"], "modes": ["SPM", "PDI", "XMEGAJTAG"]},
  {"partno": "x64b3", "names": ["ATxmega64B3"], "modes": ["SPM", "PDI", "XMEGAJTAG"]},
  {"partno": "x64c3", "names": ["ATxmega64C3"], "modes": ["SPM", "PDI"]},
  {"partno": "x64d3", "names": ["ATxmega64D3"], "modes": ["SPM", "PDI"]},
  {"partno": "x64d4", "names": ["ATxmega64D4"], "modes": ["SPM", "PDI"]},
  {"partno": "x8e5", "names": ["ATxmega8E5"], "modes": ["SPM", "PDI"]},
  {"partno": "128da28", "names": ["AVR128DA28", "AVR128DA28T"], "modes": ["SPM", "UPDI"]},
  {"partno": "128da28s", "names": ["AVR128DA28S"], "modes": ["SPM", "UPDI"]},
  {"partno": "128da32", "names": ["AVR128DA32", "AVR128DA32T"], "modes": ["SPM", "UPDI"]},
  {"partno": "128da32s", "names": ["AVR128DA32S"], "modes": ["SPM", "UPDI"]},
  {"partno": "128da48", "names": ["AVR128DA48", "AVR128DA48T"], "modes": ["SPM", "UPDI"]},
  {"partno": "128da48s", "names": ["AVR128DA48S"], "modes": ["SPM", "UPDI"]},
  {"partno": "128da64", "names": ["AVR128DA64", "AVR128DA64T"], "modes": ["SPM", "UPDI"]},
  {"partno": "128da64s", "names": ["AVR128DA64S"], "modes": ["SPM", "UPDI"]},
  {"partno": "128db28", "names": ["AVR128DB28", "AVR128DB28T"], "modes": ["SPM", "UPDI"]},
  {"partno": "128db32", "names": ["AVR128DB32", "AVR128DB32T"], "modes": ["SPM", "UPDI"]},
  {"partno": "128db48", "names": ["AVR128DB48", "AVR128DB48T"], "modes": ["SPM", "UPDI"]},
  {"partno": "128db64", "names": ["AVR128DB64", "AVR128DB64T"], "modes": ["SPM", "UPDI"]},
  {"partno": "16dd14", "names": ["AVR16DD14"], "modes": ["SPM", "UPDI"]},
  {"partno": "16dd20", "names": ["AVR16DD20"], "modes": ["SPM", "UPDI"]},
  {"partno": "16dd28", "names": ["AVR16DD28"], "modes": ["SPM", "UPDI"]},
  {"partno": "16dd32", "names": ["AVR16DD32"], "modes": ["SPM", "UPDI"]},
  {"partno": "16du14", "names": ["AVR16DU14"], "modes": ["SPM", "UPDI"]},
  {"partno": "16du20", "names": ["AVR16DU20"], "modes": ["SPM", "UPDI"]},
  {"partno": "16du28", "names": ["AVR16DU28"], "modes": ["SPM", "UPDI"]},
  {"partno": "16du32", "names": ["AVR16DU32"], "modes": ["SPM", "UPDI"]},
  {"partno": "16ea28", "names": ["AVR16EA28"], "modes": ["SPM", "UPDI"]},
  {"partno": "16ea32", "names": ["AVR16EA32"], "modes": ["SPM", "UPDI"]},
  {"partno": "16ea48", "names": ["AVR16EA48"], "modes": ["SPM", "UPDI"]},
  {"partno": "16eb14", "names": ["AVR16EB14"], "modes": ["SPM", "UPDI"]},
  {"partno": "16eb20", "names": ["AVR16EB20"], "modes": ["SPM", "UPDI"]},
  {"partno": "16eb28", "names": ["AVR16EB28"], "modes": ["SPM", "UPDI"]},
  {"partno": "16eb32", "names": ["AVR16EB32"], "modes": ["SPM", "UPDI"]},
  {"partno": "32da28", "names": ["AVR32DA28", "AVR32DA28T"], "modes": ["SPM", "UPDI"]},
  {"partno": "32da28s", "names": ["AVR32DA28S"], "modes": ["SPM", "UPDI"]},
  {"partno": "32da32", "names": ["AVR32DA32", "AVR32DA32T"], "modes": ["SPM", "UPDI"]},
  {"partno": "32da32s", "names": ["AVR32DA32S"], "modes": ["SPM", "UPDI"]},
  {"partno": "32da48", "names": ["AVR32DA48", "AVR32DA48T"], "modes": ["SPM", "UPDI"]},
  {"partno": "32da48s", "names": ["AVR32DA48S"], "modes": ["SPM", "UPDI"]},
  {"partno": "32db28", "names": ["AVR32DB28", "AVR32DB28T"], "modes": ["SPM", "UPDI"]},
  {"partno": "32db32", "names": ["AVR32DB32", "AVR32DB32T"], "modes": ["SPM", "UPDI"]},
  {"partno": "32db48", "names": ["AVR32DB48", "AVR32DB48T"], "modes": ["SPM", "UPDI"]},
  {"partno": "32dd14", "names": ["AVR32DD14"], "modes": ["SPM", "UPDI"]},
  {"partno": "32dd20", "names": ["AVR32DD20"], "modes": ["SPM", "UPDI"]},
  {"partno": "32dd28", "names": ["AVR32DD28"], "modes": ["SPM", "UPDI"]},
  {"partno": "32dd32", "names": ["AVR32DD32"], "modes": ["SPM", "UPDI"]},
  {"partno": "32du14", "names": ["AVR32DU14"], "modes": ["SPM", "UPDI"]},
  {"partno": "32du20", "names": ["AVR32DU20"], "modes": ["SPM", "UPDI"]},
  {"partno": "32du28", "names": ["AVR32DU28"], "modes": ["SPM", "UPDI"]},
  {"partno": "32du32", "names": ["AVR32DU32"], "modes": ["SPM", "UPDI"]},
  {"partno": "32ea28", "names": ["AVR32EA28"], "modes": ["SPM", "UPDI"]},
  {"partno": "32ea32", "names": ["AVR32EA32"], "modes": ["SPM", "UPDI"]},
  {"partno": "32ea48", "names": ["AVR32EA48"], "modes": ["SPM", "UPDI"]},
  {"partno": "32eb14", "names": ["AVR32EB14"], "modes": ["SPM", "UPDI"]},
  {"partno": "32eb20", "names": ["AVR32EB20"], "modes": ["SPM", "UPDI"]},
  {"partno": "32eb28", "names": ["AVR32EB28"], "modes": ["SPM", "UPDI"]},
  {"partno": "32eb32", "names": ["AVR32EB32"], "modes": ["SPM", "UPDI"]},
  {"partno": "32sd20", "names": ["AVR32SD20"], "modes": ["SPM", "UPDI"]},
  {"partno": "32sd28", "names": ["AVR32SD28"], "modes": ["SPM", "UPDI"]},
  {"partno": "32sd32", "names": ["AVR32SD32"], "modes": ["SPM", "UPDI"]},
  {"partno": "64da28", "names": ["AVR64DA28", "AVR64DA28T"], "modes": ["SPM", "UPDI"]},
  {"partno": "64da28s", "names": ["AVR64DA28S"], "modes": ["SPM", "UPDI"]},
  {"partno": "64da32", "names": ["AVR64DA32", "AVR64DA32T"], "modes": ["SPM", "UPDI"]},
  {"partno": "64da32s", "names": ["AVR64DA32S"], "modes": ["SPM", "UPDI"]},
  {"partno": "64da48", "names": ["AVR64DA48", "AVR64DA48T"], "modes": ["SPM", "UPDI"]},
  {"partno": "64da48s", "names": ["AVR64DA48S"], "modes": ["SPM", "UPDI"]},
  {"partno": "64da64", "names": ["AVR64DA64", "AVR64DA64T"], "modes": ["SPM", "UPDI"]},
  {"partno": "64da64s", "names": ["AVR64DA64S"], "modes": ["SPM", "UPDI"]},
  {"partno": "64db28", "names": ["AVR64DB28", "AVR64DB28T"], "modes": ["SPM", "UPDI"]},
  {"partno": "64db32", "names": ["AVR64DB32", "AVR64DB32T"], "modes": ["SPM", "UPDI"]},
  {"partno": "64db48", "names": ["AVR64DB48", "AVR64DB48T"], "modes": ["SPM", "UPDI"]},
  {"partno": "64db64", "names": ["AVR64DB64", "AVR64DB64T"], "modes": ["SPM", "UPDI"]},
  {"partno": "64dd14", "names": ["AVR64DD14"], "modes": ["SPM", "UPDI"]},
  {"partno": "64dd20", "names": ["AVR64DD20"], "modes": ["SPM", "UPDI"]},
  {"partno": "64dd28", "names": ["AVR64DD28"], "modes": ["SPM", "UPDI"]},
  {"partno": "64dd32", "names": ["AVR64DD32"], "modes": ["SPM", "UPDI"]},
  {"partno": "64du28", "names": ["AVR64DU28"], "modes": ["SPM", "UPDI"]},
  {"partno": "64du32", "names": ["AVR64DU32"], "modes": ["SPM", "UPDI"]},
  {"partno": "64ea28", "names": ["AVR64EA28"], "modes": ["SPM", "UPDI"]},
  {"partno": "64ea32", "names": ["AVR64EA32"], "modes": ["SPM", "UPDI"]},
  {"partno": "64ea48", "names": ["AVR64EA48"], "modes": ["SPM", "UPDI"]},
  {"partno": "8ea28", "names": ["AVR8EA28"], "modes": ["SPM", "UPDI"]},
  {"partno": "8ea32", "names": ["AVR8EA32"], "modes": ["SPM", "UPDI"]},
  {"partno": "lgt168p", "names": ["LGT8F168P"], "modes": ["SPM", "ISP", "HVPP", "debugWIRE"]},
  {"partno": "lgt328p", "names": ["LGT8F328P"], "modes": ["SPM", "ISP", "HVPP", "debugWIRE"]},
  {"partno": "lgt88p", "names": ["LGT8F88P"], "modes": ["SPM", "ISP", "HVPP", "debugWIRE"]}
]
